bpmn_widget/__init__.py
bpmn_widget/apps.py
bpmn_widget/widgets.py
bpmn_widget/static/django_bpmn_widget/bpmn-integration-properties-panel.js
bpmn_widget/static/django_bpmn_widget/bpmn-js/assets/bpmn-js.css
bpmn_widget/static/django_bpmn_widget/bpmn-js/assets/diagram-js.css
bpmn_widget/static/django_bpmn_widget/bpmn-js/assets/bpmn-font/css/bpmn-codes.css
bpmn_widget/static/django_bpmn_widget/bpmn-js/assets/bpmn-font/css/bpmn-embedded.css
bpmn_widget/static/django_bpmn_widget/bpmn-js/assets/bpmn-font/css/bpmn.css
bpmn_widget/static/django_bpmn_widget/bpmn-js/assets/bpmn-font/font/bpmn.eot
bpmn_widget/static/django_bpmn_widget/bpmn-js/assets/bpmn-font/font/bpmn.svg
bpmn_widget/static/django_bpmn_widget/bpmn-js/assets/bpmn-font/font/bpmn.ttf
bpmn_widget/static/django_bpmn_widget/bpmn-js/assets/bpmn-font/font/bpmn.woff
bpmn_widget/static/django_bpmn_widget/bpmn-js/assets/bpmn-font/font/bpmn.woff2
bpmn_widget/static/django_bpmn_widget/bpmn-js-properties-panel/assets/element-templates.css
bpmn_widget/static/django_bpmn_widget/bpmn-js-properties-panel/assets/properties-panel.css
bpmn_widget/templates/django_bpmn_widget/bpmn.html
django_bpmn_widget-1.0.1.dist-info/LICENSE
django_bpmn_widget-1.0.1.dist-info/METADATA
django_bpmn_widget-1.0.1.dist-info/WHEEL
django_bpmn_widget-1.0.1.dist-info/top_level.txt
django_bpmn_widget-1.0.1.dist-info/RECORD
