Metadata-Version: 2.1
Name: django-bpmn-widget
Version: 1.0.1
Summary: django bpmn modeler widget(integrated with properties panel)
Home-page: https://github.com/walirt/django-bpmn-widget
Author: walirt
Author-email: 610577219@qq.com
Project-URL: Source, https://github.com/walirt/django-bpmn-widget
Project-URL: Bug Reports, https://github.com/walirt/django-bpmn-widget/issues
Keywords: django,bpmn,widget
Classifier: Framework :: Django
Classifier: Programming Language :: Python :: 3
Classifier: License :: OSI Approved :: MIT License
Classifier: Operating System :: OS Independent
Requires-Python: >=3
License-File: LICENSE
Requires-Dist: Django
